metapensiero/deform/semantic_ui/__init__.py
metapensiero/deform/semantic_ui/pyramid.py
metapensiero_deform_semantic_ui-1.1.data/platlib/metapensiero/deform/semantic_ui/templates/autocomplete_input.pt
metapensiero_deform_semantic_ui-1.1.data/platlib/metapensiero/deform/semantic_ui/templates/checkbox.pt
metapensiero_deform_semantic_ui-1.1.data/platlib/metapensiero/deform/semantic_ui/templates/checkbox_choice.pt
metapensiero_deform_semantic_ui-1.1.data/platlib/metapensiero/deform/semantic_ui/templates/checked_input.pt
metapensiero_deform_semantic_ui-1.1.data/platlib/metapensiero/deform/semantic_ui/templates/checked_password.pt
metapensiero_deform_semantic_ui-1.1.data/platlib/metapensiero/deform/semantic_ui/templates/dateinput.pt
metapensiero_deform_semantic_ui-1.1.data/platlib/metapensiero/deform/semantic_ui/templates/dateparts.pt
metapensiero_deform_semantic_ui-1.1.data/platlib/metapensiero/deform/semantic_ui/templates/datetimeinput.pt
metapensiero_deform_semantic_ui-1.1.data/platlib/metapensiero/deform/semantic_ui/templates/file_upload.pt
metapensiero_deform_semantic_ui-1.1.data/platlib/metapensiero/deform/semantic_ui/templates/form.pt
metapensiero_deform_semantic_ui-1.1.data/platlib/metapensiero/deform/semantic_ui/templates/hidden.pt
metapensiero_deform_semantic_ui-1.1.data/platlib/metapensiero/deform/semantic_ui/templates/mapping.pt
metapensiero_deform_semantic_ui-1.1.data/platlib/metapensiero/deform/semantic_ui/templates/mapping_accordion.pt
metapensiero_deform_semantic_ui-1.1.data/platlib/metapensiero/deform/semantic_ui/templates/mapping_item.pt
metapensiero_deform_semantic_ui-1.1.data/platlib/metapensiero/deform/semantic_ui/templates/moneyinput.pt
metapensiero_deform_semantic_ui-1.1.data/platlib/metapensiero/deform/semantic_ui/templates/password.pt
metapensiero_deform_semantic_ui-1.1.data/platlib/metapensiero/deform/semantic_ui/templates/radio_choice.pt
metapensiero_deform_semantic_ui-1.1.dist-info/METADATA
metapensiero_deform_semantic_ui-1.1.dist-info/WHEEL
metapensiero_deform_semantic_ui-1.1.dist-info/entry_points.txt
metapensiero_deform_semantic_ui-1.1.dist-info/RECORD
